AiohttpZhongwenWendang/README.md
AiohttpZhongwenWendang/__init__.py
AiohttpZhongwenWendang/__main__.py
AiohttpZhongwenWendang/file.epub
AiohttpZhongwenWendang/index.html
AiohttpZhongwenWendang/css/__init__.py
AiohttpZhongwenWendang/css/annotations.css
AiohttpZhongwenWendang/css/main.css
AiohttpZhongwenWendang/css/normalize.css
AiohttpZhongwenWendang/css/popup.css
AiohttpZhongwenWendang/font/__init__.py
AiohttpZhongwenWendang/font/fontello.eot
AiohttpZhongwenWendang/font/fontello.svg
AiohttpZhongwenWendang/font/fontello.ttf
AiohttpZhongwenWendang/font/fontello.woff
AiohttpZhongwenWendang/img/__init__.py
AiohttpZhongwenWendang/img/annotator-glyph-sprite.png
AiohttpZhongwenWendang/img/annotator-icon-sprite.png
AiohttpZhongwenWendang/img/apple-touch-icon.png
AiohttpZhongwenWendang/img/cancelfullscreen.png
AiohttpZhongwenWendang/img/close.png
AiohttpZhongwenWendang/img/fullscreen.png
AiohttpZhongwenWendang/img/loader.gif
AiohttpZhongwenWendang/img/menu-icon.png
AiohttpZhongwenWendang/img/save.png
AiohttpZhongwenWendang/img/saved.png
AiohttpZhongwenWendang/img/settings-s.png
AiohttpZhongwenWendang/img/settings.png
AiohttpZhongwenWendang/img/star.png
AiohttpZhongwenWendang/js/__init__.py
AiohttpZhongwenWendang/js/epub.js
AiohttpZhongwenWendang/js/epub.min.js
AiohttpZhongwenWendang/js/epub.min.map
AiohttpZhongwenWendang/js/hooks.min.js
AiohttpZhongwenWendang/js/hooks.min.map
AiohttpZhongwenWendang/js/reader.js
AiohttpZhongwenWendang/js/reader.js.map
AiohttpZhongwenWendang/js/reader.min.js
AiohttpZhongwenWendang/js/reader.min.map
AiohttpZhongwenWendang/js/hooks/__init__.py
AiohttpZhongwenWendang/js/hooks/extensions/__init__.py
AiohttpZhongwenWendang/js/hooks/extensions/highlight.js
AiohttpZhongwenWendang/js/libs/__init__.py
AiohttpZhongwenWendang/js/libs/jquery.min.js
AiohttpZhongwenWendang/js/libs/localforage.min.js
AiohttpZhongwenWendang/js/libs/screenfull.js
AiohttpZhongwenWendang/js/libs/screenfull.min.js
AiohttpZhongwenWendang/js/libs/zip.min.js
aiohttp_zhongwen_wendang-2024.3.3.0.dist-info/METADATA
aiohttp_zhongwen_wendang-2024.3.3.0.dist-info/WHEEL
aiohttp_zhongwen_wendang-2024.3.3.0.dist-info/entry_points.txt
aiohttp_zhongwen_wendang-2024.3.3.0.dist-info/top_level.txt
aiohttp_zhongwen_wendang-2024.3.3.0.dist-info/RECORD
